[
    {
        "name": "exceptiongroup",
        "version": "1.2.2"
    },
    {
        "name": "execnet",
        "version": "2.1.1"
    },
    {
        "name": "iniconfig",
        "version": "2.0.0"
    },
    {
        "name": "packaging",
        "version": "24.2"
    },
    {
        "name": "pip",
        "version": "24.3.1"
    },
    {
        "name": "pipdeptree",
        "version": "2.24.0"
    },
    {
        "name": "pluggy",
        "version": "1.5.0"
    },
    {
        "name": "pycryptodome",
        "version": "3.21.0"
    },
    {
        "name": "pytest",
        "version": "8.3.4"
    },
    {
        "name": "pytest-xdist",
        "version": "3.6.1"
    },
    {
        "name": "scapy",
        "version": "2.6.0"
    },
    {
        "name": "setuptools",
        "version": "65.5.1"
    },
    {
        "name": "tomli",
        "version": "2.2.1"
    },
    {
        "name": "wheel",
        "version": "0.45.1"
    }
]