[
    {
        "command": "ls /repo",
        "returncode": 0,
        "time": 0.61067795753479,
        "dir": "/"
    },
    {
        "command": "pipdeptree --json-tree",
        "returncode": 0,
        "time": 0.8838176727294922,
        "dir": "/"
    },
    {
        "command": "pipdeptree",
        "returncode": 0,
        "time": 0.9389920234680176,
        "dir": "/"
    },
    {
        "command": "python /home/tools/generate_diff.py",
        "returncode": 0,
        "time": 0.7688806056976318,
        "dir": "/"
    },
    {
        "command": "cat /repo/pyproject.toml",
        "returncode": 0,
        "time": 0.607651948928833,
        "dir": "/"
    },
    {
        "command": "pipdeptree --json-tree",
        "returncode": 0,
        "time": 0.854464054107666,
        "dir": "/"
    },
    {
        "command": "pipdeptree",
        "returncode": 0,
        "time": 0.857102632522583,
        "dir": "/"
    },
    {
        "command": "python /home/tools/generate_diff.py",
        "returncode": 0,
        "time": 0.6449873447418213,
        "dir": "/"
    },
    {
        "command": "cd /repo",
        "returncode": 0,
        "time": 0.6071140766143799,
        "dir": "/"
    },
    {
        "command": "poetry install",
        "returncode": 1,
        "time": 1.0167484283447266,
        "dir": "/repo"
    },
    {
        "command": "pipdeptree --json-tree",
        "returncode": 0,
        "time": 0.8573949337005615,
        "dir": "/"
    },
    {
        "command": "pipdeptree",
        "returncode": 0,
        "time": 0.8536365032196045,
        "dir": "/"
    },
    {
        "command": "python /home/tools/generate_diff.py",
        "returncode": 0,
        "time": 0.7666144371032715,
        "dir": "/"
    },
    {
        "command": "ls /repo",
        "returncode": 0,
        "time": 0.608452320098877,
        "dir": "/"
    },
    {
        "command": "pipdeptree --json-tree",
        "returncode": 0,
        "time": 0.8605291843414307,
        "dir": "/"
    },
    {
        "command": "pipdeptree",
        "returncode": 0,
        "time": 0.8716127872467041,
        "dir": "/"
    },
    {
        "command": "python /home/tools/generate_diff.py",
        "returncode": 0,
        "time": 0.654608964920044,
        "dir": "/"
    },
    {
        "command": "ls /repo/requirements",
        "returncode": 0,
        "time": 0.6084766387939453,
        "dir": "/"
    },
    {
        "command": "pipdeptree --json-tree",
        "returncode": 0,
        "time": 0.9076099395751953,
        "dir": "/"
    },
    {
        "command": "pipdeptree",
        "returncode": 0,
        "time": 0.8708798885345459,
        "dir": "/"
    },
    {
        "command": "python /home/tools/generate_diff.py",
        "returncode": 0,
        "time": 0.6479225158691406,
        "dir": "/"
    },
    {
        "command": "pipdeptree --json-tree",
        "returncode": 0,
        "time": 0.8867912292480469,
        "dir": "/"
    },
    {
        "command": "pipdeptree",
        "returncode": 0,
        "time": 0.8482322692871094,
        "dir": "/"
    },
    {
        "command": "python /home/tools/generate_diff.py",
        "returncode": 0,
        "time": 0.6463913917541504,
        "dir": "/"
    },
    {
        "command": "cat /repo/requirements/required.txt",
        "returncode": 0,
        "time": 0.6076691150665283,
        "dir": "/"
    },
    {
        "command": "pipdeptree --json-tree",
        "returncode": 0,
        "time": 0.8620865345001221,
        "dir": "/"
    },
    {
        "command": "pipdeptree",
        "returncode": 0,
        "time": 0.8689286708831787,
        "dir": "/"
    },
    {
        "command": "python /home/tools/generate_diff.py",
        "returncode": 0,
        "time": 0.6476688385009766,
        "dir": "/"
    },
    {
        "command": "pipdeptree --json-tree",
        "returncode": 0,
        "time": 0.8916141986846924,
        "dir": "/"
    },
    {
        "command": "pipdeptree",
        "returncode": 0,
        "time": 0.8873195648193359,
        "dir": "/"
    },
    {
        "command": "python /home/tools/generate_diff.py",
        "returncode": 0,
        "time": 0.6474595069885254,
        "dir": "/"
    },
    {
        "command": "pipdeptree --json-tree",
        "returncode": 0,
        "time": 0.8580114841461182,
        "dir": "/"
    },
    {
        "command": "pipdeptree",
        "returncode": 0,
        "time": 0.8707995414733887,
        "dir": "/"
    },
    {
        "command": "python /home/tools/generate_diff.py",
        "returncode": 0,
        "time": 0.6436386108398438,
        "dir": "/"
    },
    {
        "command": "python /home/tools/pip_download.py -p torchgeo -v \"\"==0.6.0\"\"",
        "returncode": 0,
        "time": 259.4795172214508,
        "dir": "/"
    },
    {
        "command": "python /home/tools/pip_download.py -p rioxarray -v \"\"==0.15.0\"\"",
        "returncode": 0,
        "time": 4.067375183105469,
        "dir": "/"
    },
    {
        "command": "python /home/tools/pip_download.py -p albumentations -v \"\"==1.3.1\"\"",
        "returncode": 0,
        "time": 14.621793746948242,
        "dir": "/"
    },
    {
        "command": "python /home/tools/pip_download.py -p albucore -v \"\"<=0.0.16\"\"",
        "returncode": 1,
        "time": 0.052829742431640625,
        "dir": "/"
    },
    {
        "command": "python /home/tools/pip_download.py -p rasterio -v \"\"==1.3.10\"\"",
        "returncode": 0,
        "time": 3.530195951461792,
        "dir": "/"
    },
    {
        "command": "python /home/tools/pip_download.py -p torch -v \"\"==2.3.1\"\"",
        "returncode": 0,
        "time": 108.58589172363281,
        "dir": "/"
    },
    {
        "command": "python /home/tools/pip_download.py -p torchvision -v \"\"==0.18.1\"\"",
        "returncode": 0,
        "time": 2.911268711090088,
        "dir": "/"
    },
    {
        "command": "python /home/tools/pip_download.py -p torchmetrics -v \"\"==1.4.0\"\"",
        "returncode": 0,
        "time": 3.1056246757507324,
        "dir": "/"
    },
    {
        "command": "python /home/tools/pip_download.py -p geopandas -v \"\"==0.14.4\"\"",
        "returncode": 0,
        "time": 3.013054609298706,
        "dir": "/"
    },
    {
        "command": "python /home/tools/pip_download.py -p lightly -v \"\"==1.4.25\"\"",
        "returncode": 0,
        "time": 4.145945310592651,
        "dir": "/"
    },
    {
        "command": "python /home/tools/pip_download.py -p h5py -v \"\"==3.12.1\"\"",
        "returncode": 0,
        "time": 2.4842209815979004,
        "dir": "/"
    },
    {
        "command": "python /home/tools/pip_download.py -p mlflow -v \"\"==2.14.3\"\"",
        "returncode": 0,
        "time": 18.748106479644775,
        "dir": "/"
    },
    {
        "command": "python /home/tools/pip_download.py -p lightning -v \"\"==2.4.0\"\"",
        "returncode": 0,
        "time": 3.2879769802093506,
        "dir": "/"
    },
    {
        "command": "python /home/tools/pip_download.py -p segmentation-models-pytorch -v \"\"==0.3.4\"\"",
        "returncode": 0,
        "time": 2.14190411567688,
        "dir": "/"
    },
    {
        "command": "python /home/tools/pip_download.py -p albucore -v \"\"<=0.0.16\"\"",
        "returncode": 1,
        "time": 0.053693532943725586,
        "dir": "/"
    },
    {
        "command": "python /home/tools/pip_download.py -p albucore -v \"\"<=0.0.16\"\"",
        "returncode": 1,
        "time": 0.053412675857543945,
        "dir": "/"
    },
    {
        "command": "pipdeptree --json-tree",
        "returncode": 0,
        "time": 2.1548686027526855,
        "dir": "/"
    },
    {
        "command": "pipdeptree",
        "returncode": 0,
        "time": 2.8090951442718506,
        "dir": "/"
    },
    {
        "command": "python /home/tools/generate_diff.py",
        "returncode": 0,
        "time": 0.649238109588623,
        "dir": "/"
    },
    {
        "command": "pipdeptree --json-tree",
        "returncode": 0,
        "time": 2.61600661277771,
        "dir": "/"
    },
    {
        "command": "pipdeptree",
        "returncode": 0,
        "time": 2.6587162017822266,
        "dir": "/"
    },
    {
        "command": "python /home/tools/generate_diff.py",
        "returncode": 0,
        "time": 0.6441695690155029,
        "dir": "/"
    },
    {
        "command": "cat /repo/requirements/dev.txt",
        "returncode": 0,
        "time": 0.6075677871704102,
        "dir": "/"
    },
    {
        "command": "cat /repo/requirements/test.txt",
        "returncode": 0,
        "time": 0.6079413890838623,
        "dir": "/"
    },
    {
        "command": "pipdeptree --json-tree",
        "returncode": 0,
        "time": 2.1319501399993896,
        "dir": "/"
    },
    {
        "command": "pipdeptree",
        "returncode": 0,
        "time": 3.141676664352417,
        "dir": "/"
    },
    {
        "command": "python /home/tools/generate_diff.py",
        "returncode": 0,
        "time": 0.654383659362793,
        "dir": "/"
    },
    {
        "command": "pipdeptree --json-tree",
        "returncode": 0,
        "time": 2.2236077785491943,
        "dir": "/"
    },
    {
        "command": "pipdeptree",
        "returncode": 0,
        "time": 2.770402669906616,
        "dir": "/"
    },
    {
        "command": "python /home/tools/generate_diff.py",
        "returncode": 0,
        "time": 0.6436789035797119,
        "dir": "/"
    },
    {
        "command": "python /home/tools/pip_download.py -p mkdocs-material -v \"\"==9.4.14\"\"",
        "returncode": 0,
        "time": 9.741015911102295,
        "dir": "/"
    },
    {
        "command": "python /home/tools/pip_download.py -p mkdocstrings[python]",
        "returncode": 0,
        "time": 3.253455638885498,
        "dir": "/"
    },
    {
        "command": "python /home/tools/pip_download.py -p h5py -v \"\"==3.12.1\"\"",
        "returncode": 0,
        "time": 2.1756443977355957,
        "dir": "/"
    },
    {
        "command": "python /home/tools/pip_download.py -p jupyterlab",
        "returncode": 0,
        "time": 16.90725588798523,
        "dir": "/"
    },
    {
        "command": "python /home/tools/pip_download.py -p coverage[toml] -v \"\">=6.5\"\"",
        "returncode": 0,
        "time": 3.2158498764038086,
        "dir": "/"
    },
    {
        "command": "python /home/tools/pip_download.py -p pytest-cov -v \"\"==4.1.0\"\"",
        "returncode": 0,
        "time": 2.56251859664917,
        "dir": "/"
    },
    {
        "command": "python /home/tools/pip_download.py -p pytest -v \"\"==8.3.3\"\"",
        "returncode": 0,
        "time": 3.6575827598571777,
        "dir": "/"
    },
    {
        "command": "pipdeptree --json-tree",
        "returncode": 0,
        "time": 2.7151601314544678,
        "dir": "/"
    },
    {
        "command": "pipdeptree",
        "returncode": 0,
        "time": 3.433119773864746,
        "dir": "/"
    },
    {
        "command": "python /home/tools/generate_diff.py",
        "returncode": 0,
        "time": 0.6499521732330322,
        "dir": "/"
    },
    {
        "command": "python /home/tools/runtest.py",
        "returncode": 0,
        "time": 16.6344997882843,
        "dir": "/"
    },
    {
        "command": "pipdeptree --json-tree",
        "returncode": 0,
        "time": 2.8265609741210938,
        "dir": "/"
    },
    {
        "command": "pipdeptree",
        "returncode": 0,
        "time": 3.3971705436706543,
        "dir": "/"
    },
    {
        "command": "python /home/tools/generate_diff.py",
        "returncode": 0,
        "time": 0.6468732357025146,
        "dir": "/"
    }
]