[
    {
        "command": "ls /repo",
        "returncode": 0,
        "time": 0.609328031539917,
        "dir": "/"
    },
    {
        "command": "pipdeptree --json-tree",
        "returncode": 0,
        "time": 0.896744966506958,
        "dir": "/"
    },
    {
        "command": "pipdeptree",
        "returncode": 0,
        "time": 0.8757357597351074,
        "dir": "/"
    },
    {
        "command": "python /home/tools/generate_diff.py",
        "returncode": 0,
        "time": 0.7620961666107178,
        "dir": "/"
    },
    {
        "command": "cat /repo/pyproject.toml",
        "returncode": 0,
        "time": 0.6078011989593506,
        "dir": "/"
    },
    {
        "command": "pipdeptree --json-tree",
        "returncode": 0,
        "time": 0.8785500526428223,
        "dir": "/"
    },
    {
        "command": "pipdeptree",
        "returncode": 0,
        "time": 0.9177460670471191,
        "dir": "/"
    },
    {
        "command": "python /home/tools/generate_diff.py",
        "returncode": 0,
        "time": 0.6418402194976807,
        "dir": "/"
    },
    {
        "command": "cd /repo",
        "returncode": 0,
        "time": 0.6062932014465332,
        "dir": "/"
    },
    {
        "command": "poetry install",
        "returncode": 1,
        "time": 1.5668184757232666,
        "dir": "/repo"
    },
    {
        "command": "pipdeptree --json-tree",
        "returncode": 0,
        "time": 0.8815114498138428,
        "dir": "/"
    },
    {
        "command": "pipdeptree",
        "returncode": 0,
        "time": 0.8534011840820312,
        "dir": "/"
    },
    {
        "command": "python /home/tools/generate_diff.py",
        "returncode": 0,
        "time": 0.6477539539337158,
        "dir": "/"
    },
    {
        "command": "cat /repo/setup.cfg",
        "returncode": 0,
        "time": 0.608201265335083,
        "dir": "/"
    },
    {
        "command": "pipdeptree --json-tree",
        "returncode": 0,
        "time": 0.8783786296844482,
        "dir": "/"
    },
    {
        "command": "pipdeptree",
        "returncode": 0,
        "time": 0.9103410243988037,
        "dir": "/"
    },
    {
        "command": "python /home/tools/generate_diff.py",
        "returncode": 0,
        "time": 0.6411948204040527,
        "dir": "/"
    },
    {
        "command": "cat /repo/README.md",
        "returncode": 0,
        "time": 0.608102560043335,
        "dir": "/"
    },
    {
        "command": "pipdeptree --json-tree",
        "returncode": 0,
        "time": 0.8679814338684082,
        "dir": "/"
    },
    {
        "command": "pipdeptree",
        "returncode": 0,
        "time": 0.8901097774505615,
        "dir": "/"
    },
    {
        "command": "python /home/tools/generate_diff.py",
        "returncode": 0,
        "time": 0.6423435211181641,
        "dir": "/"
    },
    {
        "command": "pip install -q jinja2 setuptools>=45 setuptools_scm[toml]>=6.2",
        "returncode": 0,
        "time": 2.1093335151672363,
        "dir": "/"
    },
    {
        "command": "pipdeptree --json-tree",
        "returncode": 0,
        "time": 0.8895969390869141,
        "dir": "/"
    },
    {
        "command": "pipdeptree",
        "returncode": 0,
        "time": 0.8968002796173096,
        "dir": "/"
    },
    {
        "command": "python /home/tools/generate_diff.py",
        "returncode": 0,
        "time": 0.6638739109039307,
        "dir": "/"
    },
    {
        "command": "pip install -q pre-commit pytest pytest-benchmark mkdocs mkdocs-material mkdocs-section-index mkdocs-git-committers-plugin-2 mkdocs-git-revision-date-localized-plugin",
        "returncode": 0,
        "time": 24.150421142578125,
        "dir": "/"
    },
    {
        "command": "pipdeptree --json-tree",
        "returncode": 0,
        "time": 1.0231695175170898,
        "dir": "/"
    },
    {
        "command": "pipdeptree",
        "returncode": 0,
        "time": 1.0593199729919434,
        "dir": "/"
    },
    {
        "command": "python /home/tools/generate_diff.py",
        "returncode": 0,
        "time": 0.683861255645752,
        "dir": "/"
    },
    {
        "command": "python /home/tools/runtest.py",
        "returncode": 2,
        "time": 1.7592601776123047,
        "dir": "/"
    },
    {
        "command": "pipdeptree --json-tree",
        "returncode": 0,
        "time": 1.0430445671081543,
        "dir": "/"
    },
    {
        "command": "pipdeptree",
        "returncode": 0,
        "time": 1.1096217632293701,
        "dir": "/"
    },
    {
        "command": "python /home/tools/generate_diff.py",
        "returncode": 0,
        "time": 0.6451230049133301,
        "dir": "/"
    },
    {
        "command": "export PYTHONPATH=/repo",
        "returncode": 0,
        "time": 0.6064643859863281,
        "dir": "/"
    },
    {
        "command": "python /home/tools/runtest.py",
        "returncode": 0,
        "time": 2.0268609523773193,
        "dir": "/"
    },
    {
        "command": "pipdeptree --json-tree",
        "returncode": 0,
        "time": 1.1644389629364014,
        "dir": "/"
    },
    {
        "command": "pipdeptree",
        "returncode": 0,
        "time": 1.2019994258880615,
        "dir": "/"
    },
    {
        "command": "python /home/tools/generate_diff.py",
        "returncode": 0,
        "time": 0.6476340293884277,
        "dir": "/"
    }
]