[
    {
        "GPT_time": 2.2148277759552
    },
    {
        "command": "ls /repo",
        "returncode": 0,
        "time": 1.1690714359283447
    },
    {
        "GPT_time": 1.6164345741271973
    },
    {
        "command": "cat /repo/README.md",
        "returncode": 0,
        "time": 1.1653785705566406
    },
    {
        "GPT_time": 1.7806689739227295
    },
    {
        "command": "cat /repo/requirements.txt",
        "returncode": 0,
        "time": 1.1607482433319092
    },
    {
        "GPT_time": 2.430513858795166
    },
    {
        "command": "waitinglist addfile /repo/requirements.txt",
        "returncode": 0,
        "time": 0.03336644172668457
    },
    {
        "GPT_time": 2.8193728923797607
    },
    {
        "command": "download",
        "returncode": 0,
        "time": 612.0684969425201
    },
    {
        "GPT_time": 1.7689244747161865
    },
    {
        "command": "runtest",
        "returncode": 0,
        "time": 291.7845582962036
    },
    {
        "GPT_time": 2.120389938354492
    },
    {
        "command": "cat /repo/setup.py",
        "returncode": 0,
        "time": 1.160693645477295
    },
    {
        "GPT_time": 1.7274646759033203
    },
    {
        "command": "cd /repo",
        "returncode": 0,
        "time": 1.1600923538208008
    },
    {
        "command": "pip install -e .",
        "returncode": 0,
        "time": 3.285092830657959
    },
    {
        "GPT_time": 3.179630994796753
    },
    {
        "command": "runtest",
        "returncode": 0,
        "time": 7.137171745300293
    }
]