[
    {
        "command": "ls /repo",
        "returncode": 0,
        "time": 0.6079874038696289,
        "dir": "/"
    },
    {
        "command": "pipdeptree --json-tree",
        "returncode": 0,
        "time": 0.9717710018157959,
        "dir": "/"
    },
    {
        "command": "pipdeptree",
        "returncode": 0,
        "time": 0.949519157409668,
        "dir": "/"
    },
    {
        "command": "python /home/tools/generate_diff.py",
        "returncode": 0,
        "time": 1.0809953212738037,
        "dir": "/"
    },
    {
        "command": "cat /repo/requirements.txt",
        "returncode": 0,
        "time": 0.6081290245056152,
        "dir": "/"
    },
    {
        "command": "pipdeptree --json-tree",
        "returncode": 0,
        "time": 0.8563442230224609,
        "dir": "/"
    },
    {
        "command": "pipdeptree",
        "returncode": 0,
        "time": 0.8688409328460693,
        "dir": "/"
    },
    {
        "command": "python /home/tools/generate_diff.py",
        "returncode": 0,
        "time": 0.6468148231506348,
        "dir": "/"
    },
    {
        "command": "cat /repo/pyproject.toml",
        "returncode": 0,
        "time": 0.6076147556304932,
        "dir": "/"
    },
    {
        "command": "pipdeptree --json-tree",
        "returncode": 0,
        "time": 0.8795442581176758,
        "dir": "/"
    },
    {
        "command": "pipdeptree",
        "returncode": 0,
        "time": 0.8961801528930664,
        "dir": "/"
    },
    {
        "command": "python /home/tools/generate_diff.py",
        "returncode": 0,
        "time": 0.6456756591796875,
        "dir": "/"
    },
    {
        "command": "cd /repo",
        "returncode": 0,
        "time": 0.6067569255828857,
        "dir": "/"
    },
    {
        "command": "poetry install",
        "returncode": 1,
        "time": 0.9805788993835449,
        "dir": "/repo"
    },
    {
        "command": "pipdeptree --json-tree",
        "returncode": 0,
        "time": 0.8664300441741943,
        "dir": "/"
    },
    {
        "command": "pipdeptree",
        "returncode": 0,
        "time": 0.8745408058166504,
        "dir": "/"
    },
    {
        "command": "python /home/tools/generate_diff.py",
        "returncode": 0,
        "time": 1.1072273254394531,
        "dir": "/"
    },
    {
        "command": "pipdeptree --json-tree",
        "returncode": 0,
        "time": 0.859210729598999,
        "dir": "/"
    },
    {
        "command": "pipdeptree",
        "returncode": 0,
        "time": 0.951664924621582,
        "dir": "/"
    },
    {
        "command": "python /home/tools/generate_diff.py",
        "returncode": 0,
        "time": 0.6477911472320557,
        "dir": "/"
    },
    {
        "command": "python /home/tools/pip_download.py -p huggingface-hub -v \"\">=0.24.5,<1.0\"\"",
        "returncode": 1,
        "time": 0.052892446517944336,
        "dir": "/"
    },
    {
        "command": "python /home/tools/pip_download.py -p mlx -v \"\">=0.20.0,<1.0\"\"",
        "returncode": 1,
        "time": 0.05334806442260742,
        "dir": "/"
    },
    {
        "command": "python /home/tools/pip_download.py -p numpy -v \"\">=2.0.1,<3.0\"\"",
        "returncode": 1,
        "time": 0.0533602237701416,
        "dir": "/"
    },
    {
        "command": "python /home/tools/pip_download.py -p opencv-python -v \"\">=4.10.0,<5.0\"\"",
        "returncode": 1,
        "time": 0.05354809761047363,
        "dir": "/"
    },
    {
        "command": "python /home/tools/pip_download.py -p piexif -v \"\">=1.1.3,<2.0\"\"",
        "returncode": 1,
        "time": 0.0536808967590332,
        "dir": "/"
    },
    {
        "command": "python /home/tools/pip_download.py -p pillow -v \"\">=10.4.0,<11.0\"\"",
        "returncode": 1,
        "time": 0.053119659423828125,
        "dir": "/"
    },
    {
        "command": "python /home/tools/pip_download.py -p safetensors -v \"\">=0.4.4,<1.0\"\"",
        "returncode": 1,
        "time": 0.05348777770996094,
        "dir": "/"
    },
    {
        "command": "python /home/tools/pip_download.py -p sentencepiece -v \"\">=0.2.0,<1.0\"\"",
        "returncode": 1,
        "time": 0.0539400577545166,
        "dir": "/"
    },
    {
        "command": "python /home/tools/pip_download.py -p tqdm -v \"\">=4.66.5,<5.0\"\"",
        "returncode": 1,
        "time": 0.054551124572753906,
        "dir": "/"
    },
    {
        "command": "python /home/tools/pip_download.py -p transformers -v \"\">=4.44.0,<5.0\"\"",
        "returncode": 1,
        "time": 0.053052663803100586,
        "dir": "/"
    },
    {
        "command": "python /home/tools/pip_download.py -p pytest -v \"\">=8.3.0,<9.0\"\"",
        "returncode": 1,
        "time": 0.05304145812988281,
        "dir": "/"
    },
    {
        "command": "python /home/tools/pip_download.py -p pytest-timer -v \"\">=1.0,<2.0\"\"",
        "returncode": 1,
        "time": 0.053229570388793945,
        "dir": "/"
    },
    {
        "command": "python /home/tools/pip_download.py -p huggingface-hub -v \"\">=0.24.5,<1.0\"\"",
        "returncode": 1,
        "time": 0.053269386291503906,
        "dir": "/"
    },
    {
        "command": "python /home/tools/pip_download.py -p mlx -v \"\">=0.20.0,<1.0\"\"",
        "returncode": 1,
        "time": 0.05394744873046875,
        "dir": "/"
    },
    {
        "command": "python /home/tools/pip_download.py -p numpy -v \"\">=2.0.1,<3.0\"\"",
        "returncode": 1,
        "time": 0.054413557052612305,
        "dir": "/"
    },
    {
        "command": "python /home/tools/pip_download.py -p opencv-python -v \"\">=4.10.0,<5.0\"\"",
        "returncode": 1,
        "time": 0.053375959396362305,
        "dir": "/"
    },
    {
        "command": "python /home/tools/pip_download.py -p piexif -v \"\">=1.1.3,<2.0\"\"",
        "returncode": 1,
        "time": 0.053484201431274414,
        "dir": "/"
    },
    {
        "command": "python /home/tools/pip_download.py -p pillow -v \"\">=10.4.0,<11.0\"\"",
        "returncode": 1,
        "time": 0.05337643623352051,
        "dir": "/"
    },
    {
        "command": "python /home/tools/pip_download.py -p safetensors -v \"\">=0.4.4,<1.0\"\"",
        "returncode": 1,
        "time": 0.06864285469055176,
        "dir": "/"
    },
    {
        "command": "python /home/tools/pip_download.py -p sentencepiece -v \"\">=0.2.0,<1.0\"\"",
        "returncode": 1,
        "time": 0.05354166030883789,
        "dir": "/"
    },
    {
        "command": "python /home/tools/pip_download.py -p tqdm -v \"\">=4.66.5,<5.0\"\"",
        "returncode": 1,
        "time": 0.05339622497558594,
        "dir": "/"
    },
    {
        "command": "python /home/tools/pip_download.py -p transformers -v \"\">=4.44.0,<5.0\"\"",
        "returncode": 1,
        "time": 0.05338764190673828,
        "dir": "/"
    },
    {
        "command": "python /home/tools/pip_download.py -p pytest -v \"\">=8.3.0,<9.0\"\"",
        "returncode": 1,
        "time": 0.059526681900024414,
        "dir": "/"
    },
    {
        "command": "python /home/tools/pip_download.py -p pytest-timer -v \"\">=1.0,<2.0\"\"",
        "returncode": 1,
        "time": 0.05309295654296875,
        "dir": "/"
    },
    {
        "command": "python /home/tools/pip_download.py -p huggingface-hub -v \"\">=0.24.5,<1.0\"\"",
        "returncode": 1,
        "time": 0.053323984146118164,
        "dir": "/"
    },
    {
        "command": "pipdeptree --json-tree",
        "returncode": 0,
        "time": 0.8867206573486328,
        "dir": "/"
    },
    {
        "command": "pipdeptree",
        "returncode": 0,
        "time": 0.8833227157592773,
        "dir": "/"
    },
    {
        "command": "python /home/tools/generate_diff.py",
        "returncode": 0,
        "time": 0.6450927257537842,
        "dir": "/"
    },
    {
        "command": "pipdeptree --json-tree",
        "returncode": 0,
        "time": 0.8545663356781006,
        "dir": "/"
    },
    {
        "command": "pipdeptree",
        "returncode": 0,
        "time": 0.8667840957641602,
        "dir": "/"
    },
    {
        "command": "python /home/tools/generate_diff.py",
        "returncode": 0,
        "time": 0.6450059413909912,
        "dir": "/"
    },
    {
        "command": "conflictlist solve -v \">=0.20.0,<1.0\"",
        "returncode": 127,
        "time": 0.10930228233337402,
        "dir": "/"
    },
    {
        "command": "pipdeptree --json-tree",
        "returncode": 0,
        "time": 0.9061660766601562,
        "dir": "/"
    },
    {
        "command": "pipdeptree",
        "returncode": 0,
        "time": 0.8573827743530273,
        "dir": "/"
    },
    {
        "command": "python /home/tools/generate_diff.py",
        "returncode": 0,
        "time": 0.6443283557891846,
        "dir": "/"
    },
    {
        "command": "pipdeptree --json-tree",
        "returncode": 0,
        "time": 0.8715560436248779,
        "dir": "/"
    },
    {
        "command": "pipdeptree",
        "returncode": 0,
        "time": 0.8669860363006592,
        "dir": "/"
    },
    {
        "command": "python /home/tools/generate_diff.py",
        "returncode": 0,
        "time": 0.6449878215789795,
        "dir": "/"
    },
    {
        "command": "pipdeptree --json-tree",
        "returncode": 0,
        "time": 0.850489616394043,
        "dir": "/"
    },
    {
        "command": "pipdeptree",
        "returncode": 0,
        "time": 0.858165979385376,
        "dir": "/"
    },
    {
        "command": "python /home/tools/generate_diff.py",
        "returncode": 0,
        "time": 0.6416110992431641,
        "dir": "/"
    },
    {
        "command": "pipdeptree --json-tree",
        "returncode": 0,
        "time": 0.857201337814331,
        "dir": "/"
    },
    {
        "command": "pipdeptree",
        "returncode": 0,
        "time": 0.848881721496582,
        "dir": "/"
    },
    {
        "command": "python /home/tools/generate_diff.py",
        "returncode": 0,
        "time": 0.6427950859069824,
        "dir": "/"
    },
    {
        "command": "pipdeptree --json-tree",
        "returncode": 0,
        "time": 0.8639390468597412,
        "dir": "/"
    },
    {
        "command": "pipdeptree",
        "returncode": 0,
        "time": 0.9412169456481934,
        "dir": "/"
    },
    {
        "command": "python /home/tools/generate_diff.py",
        "returncode": 0,
        "time": 0.6710803508758545,
        "dir": "/"
    },
    {
        "command": "pipdeptree --json-tree",
        "returncode": 0,
        "time": 0.8707430362701416,
        "dir": "/"
    },
    {
        "command": "pipdeptree",
        "returncode": 0,
        "time": 0.8650245666503906,
        "dir": "/"
    },
    {
        "command": "python /home/tools/generate_diff.py",
        "returncode": 0,
        "time": 0.6436710357666016,
        "dir": "/"
    },
    {
        "command": "pipdeptree --json-tree",
        "returncode": 0,
        "time": 0.8564424514770508,
        "dir": "/"
    },
    {
        "command": "pipdeptree",
        "returncode": 0,
        "time": 0.9025290012359619,
        "dir": "/"
    },
    {
        "command": "python /home/tools/generate_diff.py",
        "returncode": 0,
        "time": 0.6427762508392334,
        "dir": "/"
    },
    {
        "command": "pipdeptree --json-tree",
        "returncode": 0,
        "time": 0.8516848087310791,
        "dir": "/"
    },
    {
        "command": "pipdeptree",
        "returncode": 0,
        "time": 0.9479541778564453,
        "dir": "/"
    },
    {
        "command": "python /home/tools/generate_diff.py",
        "returncode": 0,
        "time": 0.6467313766479492,
        "dir": "/"
    },
    {
        "command": "pipdeptree --json-tree",
        "returncode": 0,
        "time": 0.8477051258087158,
        "dir": "/"
    },
    {
        "command": "pipdeptree",
        "returncode": 0,
        "time": 0.865696907043457,
        "dir": "/"
    },
    {
        "command": "python /home/tools/generate_diff.py",
        "returncode": 0,
        "time": 0.6481430530548096,
        "dir": "/"
    },
    {
        "command": "pipdeptree --json-tree",
        "returncode": 0,
        "time": 0.8518753051757812,
        "dir": "/"
    },
    {
        "command": "pipdeptree",
        "returncode": 0,
        "time": 0.8647801876068115,
        "dir": "/"
    },
    {
        "command": "python /home/tools/generate_diff.py",
        "returncode": 0,
        "time": 0.645930290222168,
        "dir": "/"
    },
    {
        "command": "pipdeptree --json-tree",
        "returncode": 0,
        "time": 0.8502764701843262,
        "dir": "/"
    },
    {
        "command": "pipdeptree",
        "returncode": 0,
        "time": 0.8574461936950684,
        "dir": "/"
    },
    {
        "command": "python /home/tools/generate_diff.py",
        "returncode": 0,
        "time": 0.6439766883850098,
        "dir": "/"
    },
    {
        "command": "pipdeptree --json-tree",
        "returncode": 0,
        "time": 0.9163331985473633,
        "dir": "/"
    },
    {
        "command": "pipdeptree",
        "returncode": 0,
        "time": 0.9048349857330322,
        "dir": "/"
    },
    {
        "command": "python /home/tools/generate_diff.py",
        "returncode": 0,
        "time": 0.6499066352844238,
        "dir": "/"
    },
    {
        "command": "python /home/tools/pip_download.py -p mlx -v \"\">=0.20.0,<1.0\"\"",
        "returncode": 1,
        "time": 0.053236961364746094,
        "dir": "/"
    },
    {
        "command": "pipdeptree --json-tree",
        "returncode": 0,
        "time": 0.8737421035766602,
        "dir": "/"
    },
    {
        "command": "pipdeptree",
        "returncode": 0,
        "time": 0.8872900009155273,
        "dir": "/"
    },
    {
        "command": "python /home/tools/generate_diff.py",
        "returncode": 0,
        "time": 0.6438391208648682,
        "dir": "/"
    },
    {
        "command": "python /home/tools/pip_download.py -p numpy -v \"\">=2.0.1,<3.0\"\"",
        "returncode": 1,
        "time": 0.053098440170288086,
        "dir": "/"
    },
    {
        "command": "pipdeptree --json-tree",
        "returncode": 0,
        "time": 0.8621118068695068,
        "dir": "/"
    },
    {
        "command": "pipdeptree",
        "returncode": 0,
        "time": 0.870154857635498,
        "dir": "/"
    },
    {
        "command": "python /home/tools/generate_diff.py",
        "returncode": 0,
        "time": 0.6469526290893555,
        "dir": "/"
    },
    {
        "command": "pipdeptree --json-tree",
        "returncode": 0,
        "time": 0.8671348094940186,
        "dir": "/"
    },
    {
        "command": "pipdeptree",
        "returncode": 0,
        "time": 0.8857204914093018,
        "dir": "/"
    },
    {
        "command": "python /home/tools/generate_diff.py",
        "returncode": 0,
        "time": 0.6442878246307373,
        "dir": "/"
    },
    {
        "command": "pipdeptree --json-tree",
        "returncode": 0,
        "time": 0.8467226028442383,
        "dir": "/"
    },
    {
        "command": "pipdeptree",
        "returncode": 0,
        "time": 0.8897404670715332,
        "dir": "/"
    },
    {
        "command": "python /home/tools/generate_diff.py",
        "returncode": 0,
        "time": 0.6458632946014404,
        "dir": "/"
    },
    {
        "command": "python /home/tools/pip_download.py -p opencv-python -v \"\">=4.10.0,<5.0\"\"",
        "returncode": 1,
        "time": 0.05339312553405762,
        "dir": "/"
    },
    {
        "command": "pipdeptree --json-tree",
        "returncode": 0,
        "time": 0.9160683155059814,
        "dir": "/"
    },
    {
        "command": "pipdeptree",
        "returncode": 0,
        "time": 0.866053581237793,
        "dir": "/"
    },
    {
        "command": "python /home/tools/generate_diff.py",
        "returncode": 0,
        "time": 0.6439402103424072,
        "dir": "/"
    },
    {
        "command": "python /home/tools/pip_download.py -p huggingface-hub",
        "returncode": 0,
        "time": 3.7111690044403076,
        "dir": "/"
    },
    {
        "command": "python /home/tools/pip_download.py -p mlx",
        "returncode": 0,
        "time": 2.3936574459075928,
        "dir": "/"
    },
    {
        "command": "python /home/tools/pip_download.py -p numpy",
        "returncode": 0,
        "time": 4.865924835205078,
        "dir": "/"
    },
    {
        "command": "python /home/tools/pip_download.py -p opencv-python",
        "returncode": 0,
        "time": 3.7191355228424072,
        "dir": "/"
    },
    {
        "command": "python /home/tools/pip_download.py -p piexif",
        "returncode": 0,
        "time": 1.5149798393249512,
        "dir": "/"
    },
    {
        "command": "python /home/tools/pip_download.py -p pillow",
        "returncode": 0,
        "time": 4.156642436981201,
        "dir": "/"
    },
    {
        "command": "python /home/tools/pip_download.py -p safetensors",
        "returncode": 0,
        "time": 1.9108362197875977,
        "dir": "/"
    },
    {
        "command": "python /home/tools/pip_download.py -p sentencepiece",
        "returncode": 0,
        "time": 1.772303819656372,
        "dir": "/"
    },
    {
        "command": "python /home/tools/pip_download.py -p tqdm",
        "returncode": 0,
        "time": 1.5136384963989258,
        "dir": "/"
    },
    {
        "command": "python /home/tools/pip_download.py -p transformers",
        "returncode": 0,
        "time": 11.5872802734375,
        "dir": "/"
    },
    {
        "command": "python /home/tools/pip_download.py -p pytest",
        "returncode": 0,
        "time": 1.798063039779663,
        "dir": "/"
    },
    {
        "command": "python /home/tools/pip_download.py -p pytest-timer",
        "returncode": 0,
        "time": 2.127455711364746,
        "dir": "/"
    },
    {
        "command": "pipdeptree --json-tree",
        "returncode": 0,
        "time": 1.0983760356903076,
        "dir": "/"
    },
    {
        "command": "pipdeptree",
        "returncode": 0,
        "time": 1.1712009906768799,
        "dir": "/"
    },
    {
        "command": "python /home/tools/generate_diff.py",
        "returncode": 0,
        "time": 0.6465215682983398,
        "dir": "/"
    },
    {
        "command": "python /home/tools/runtest.py",
        "returncode": 1,
        "time": 14.455185890197754,
        "dir": "/"
    },
    {
        "command": "pipdeptree --json-tree",
        "returncode": 0,
        "time": 1.0924022197723389,
        "dir": "/"
    },
    {
        "command": "pipdeptree",
        "returncode": 0,
        "time": 1.1688547134399414,
        "dir": "/"
    },
    {
        "command": "python /home/tools/generate_diff.py",
        "returncode": 0,
        "time": 0.6434154510498047,
        "dir": "/"
    },
    {
        "command": "export PYTHONPATH=\"/repo/src:$PYTHONPATH\"",
        "returncode": 0,
        "time": 0.6060988903045654,
        "dir": "/"
    },
    {
        "command": "python /home/tools/runtest.py",
        "returncode": 1,
        "time": 1.5462591648101807,
        "dir": "/"
    },
    {
        "command": "pipdeptree --json-tree",
        "returncode": 0,
        "time": 1.0820953845977783,
        "dir": "/"
    },
    {
        "command": "pipdeptree",
        "returncode": 0,
        "time": 1.1284866333007812,
        "dir": "/"
    },
    {
        "command": "python /home/tools/generate_diff.py",
        "returncode": 0,
        "time": 0.643587589263916,
        "dir": "/"
    },
    {
        "command": "apt-get update -qq",
        "returncode": 0,
        "time": 2.4589831829071045,
        "dir": "/"
    },
    {
        "command": "apt-get install libgl1-mesa-glx -y -qq",
        "returncode": 0,
        "time": 20.422799825668335,
        "dir": "/"
    },
    {
        "command": "python /home/tools/runtest.py",
        "returncode": 1,
        "time": 1.2423677444458008,
        "dir": "/"
    },
    {
        "command": "pipdeptree --json-tree",
        "returncode": 0,
        "time": 1.1449744701385498,
        "dir": "/"
    },
    {
        "command": "pipdeptree",
        "returncode": 0,
        "time": 1.1526923179626465,
        "dir": "/"
    },
    {
        "command": "python /home/tools/generate_diff.py",
        "returncode": 0,
        "time": 0.6436159610748291,
        "dir": "/"
    },
    {
        "command": "pip install -e /repo",
        "returncode": 1,
        "time": 4.53068470954895,
        "dir": "/"
    },
    {
        "command": "python /home/tools/runtest.py",
        "returncode": 1,
        "time": 1.0905382633209229,
        "dir": "/"
    },
    {
        "command": "pipdeptree --json-tree",
        "returncode": 0,
        "time": 1.14028000831604,
        "dir": "/"
    },
    {
        "command": "pipdeptree",
        "returncode": 0,
        "time": 1.4766552448272705,
        "dir": "/"
    },
    {
        "command": "python /home/tools/generate_diff.py",
        "returncode": 0,
        "time": 0.647087574005127,
        "dir": "/"
    },
    {
        "command": "pip install mlx==0.18.0 -q",
        "returncode": 0,
        "time": 1.7573657035827637,
        "dir": "/"
    },
    {
        "command": "pip install -e /repo",
        "returncode": 1,
        "time": 4.673508167266846,
        "dir": "/"
    },
    {
        "command": "pipdeptree --json-tree",
        "returncode": 0,
        "time": 1.0643270015716553,
        "dir": "/"
    },
    {
        "command": "pipdeptree",
        "returncode": 0,
        "time": 1.1463623046875,
        "dir": "/"
    },
    {
        "command": "python /home/tools/generate_diff.py",
        "returncode": 0,
        "time": 0.6435317993164062,
        "dir": "/"
    },
    {
        "command": "python /home/tools/code_edit.py -t '/tmp/patch/tmpo4d7nk67' -p '/tmp'",
        "returncode": 0,
        "time": 0.05020332336425781,
        "dir": "/"
    },
    {
        "command": "python /home/tools/generate_diff.py",
        "returncode": 0,
        "time": 0.643775463104248,
        "dir": "/"
    },
    {
        "command": "pipdeptree --json-tree",
        "returncode": 0,
        "time": 1.0632855892181396,
        "dir": "/"
    },
    {
        "command": "pipdeptree",
        "returncode": 0,
        "time": 1.1553912162780762,
        "dir": "/"
    },
    {
        "command": "python /home/tools/generate_diff.py",
        "returncode": 0,
        "time": 0.6435325145721436,
        "dir": "/"
    },
    {
        "command": "cat /repo/pyproject.toml",
        "returncode": 0,
        "time": 0.6079518795013428,
        "dir": "/"
    },
    {
        "command": "pipdeptree --json-tree",
        "returncode": 0,
        "time": 1.0881638526916504,
        "dir": "/"
    },
    {
        "command": "pipdeptree",
        "returncode": 0,
        "time": 1.1481366157531738,
        "dir": "/"
    },
    {
        "command": "python /home/tools/generate_diff.py",
        "returncode": 0,
        "time": 0.6492750644683838,
        "dir": "/"
    },
    {
        "command": "python /home/tools/code_edit.py -t '/tmp/patch/tmp9ekyz7g4' -p '/tmp'",
        "returncode": 0,
        "time": 0.050302982330322266,
        "dir": "/"
    },
    {
        "command": "python /home/tools/generate_diff.py",
        "returncode": 0,
        "time": 0.651700496673584,
        "dir": "/"
    },
    {
        "command": "pipdeptree --json-tree",
        "returncode": 0,
        "time": 1.0422823429107666,
        "dir": "/"
    },
    {
        "command": "pipdeptree",
        "returncode": 0,
        "time": 1.1305983066558838,
        "dir": "/"
    },
    {
        "command": "python /home/tools/generate_diff.py",
        "returncode": 0,
        "time": 0.643181324005127,
        "dir": "/"
    },
    {
        "command": "pip install -e /repo",
        "returncode": 0,
        "time": 161.97166228294373,
        "dir": "/"
    },
    {
        "command": "pipdeptree --json-tree",
        "returncode": 0,
        "time": 1.1253466606140137,
        "dir": "/"
    },
    {
        "command": "pipdeptree",
        "returncode": 0,
        "time": 1.6345407962799072,
        "dir": "/"
    },
    {
        "command": "python /home/tools/generate_diff.py",
        "returncode": 0,
        "time": 0.6535425186157227,
        "dir": "/"
    },
    {
        "command": "python /home/tools/runtest.py",
        "returncode": 0,
        "time": 6.162323951721191,
        "dir": "/"
    },
    {
        "command": "pipdeptree --json-tree",
        "returncode": 0,
        "time": 1.1312150955200195,
        "dir": "/"
    },
    {
        "command": "pipdeptree",
        "returncode": 0,
        "time": 1.2523717880249023,
        "dir": "/"
    },
    {
        "command": "python /home/tools/generate_diff.py",
        "returncode": 0,
        "time": 0.6468760967254639,
        "dir": "/"
    }
]